{
  "items": [
    {
      "id": "RUN-MEM-20260428-0032",
      "timestamp_start": "2026-04-28T12:54:51-03:00",
      "timestamp_end": "2026-04-28T12:54:51-03:00",
      "actor": "system",
      "squad": "SQD-MEM",
      "skill": "MemoryLifecycle",
      "module": "memory-governance",
      "entity": "dashboard",
      "action": "session_close",
      "input_summary": "Automatic lifecycle event",
      "output_summary": "Sessao SES-20260428-0016 encerrada com CHK-MEM-0295",
      "result": "success",
      "files_touched": [
        "docs/control/memory_current_state.json",
        "docs/control/memory_checkpoints.json",
        "docs/control/memory_mutations.json",
        "task.md"
      ],
      "project_id": null
    },
    {
      "id": "RUN-MEM-20260428-0033",
      "timestamp_start": "2026-04-28T12:54:53-03:00",
      "timestamp_end": "2026-04-28T12:54:53-03:00",
      "actor": "system",
      "squad": "SQD-MEM",
      "skill": "MemoryLifecycle",
      "module": "memory-governance",
      "entity": "dashboard",
      "action": "session_start",
      "input_summary": "Automatic lifecycle event",
      "output_summary": "Sessao SES-20260428-0017 iniciada",
      "result": "success",
      "files_touched": [
        "docs/control/memory_current_state.json",
        "docs/control/memory_open_loops.json",
        "docs/control/memory_checkpoints.json",
        "docs/control/memory_decision_log.json",
        "docs/memory/startup_context_latest.md",
        "task.md"
      ],
      "project_id": "sais"
    },
    {
      "id": "RUN-MEM-20260428-0034",
      "timestamp_start": "2026-04-28T12:57:42-03:00",
      "timestamp_end": "2026-04-28T12:57:42-03:00",
      "actor": "system",
      "squad": "SQD-MEM",
      "skill": "MemoryLifecycle",
      "module": "memory-governance",
      "entity": "dashboard",
      "action": "session_close",
      "input_summary": "Automatic lifecycle event",
      "output_summary": "Sessao SES-20260428-0017 encerrada com CHK-MEM-0296",
      "result": "success",
      "files_touched": [
        "docs/control/memory_current_state.json",
        "docs/control/memory_checkpoints.json",
        "docs/control/memory_mutations.json",
        "task.md"
      ],
      "project_id": null
    },
    {
      "id": "RUN-MEM-20260428-0035",
      "timestamp_start": "2026-04-28T12:57:45-03:00",
      "timestamp_end": "2026-04-28T12:57:45-03:00",
      "actor": "system",
      "squad": "SQD-MEM",
      "skill": "MemoryLifecycle",
      "module": "memory-governance",
      "entity": "dashboard",
      "action": "session_start",
      "input_summary": "Automatic lifecycle event",
      "output_summary": "Sessao SES-20260428-0018 iniciada",
      "result": "success",
      "files_touched": [
        "docs/control/memory_current_state.json",
        "docs/control/memory_open_loops.json",
        "docs/control/memory_checkpoints.json",
        "docs/control/memory_decision_log.json",
        "docs/memory/startup_context_latest.md",
        "task.md"
      ],
      "project_id": "sais"
    },
    {
      "id": "RUN-MEM-20260428-0036",
      "timestamp_start": "2026-04-28T13:05:49-03:00",
      "timestamp_end": "2026-04-28T13:05:49-03:00",
      "actor": "system",
      "squad": "SQD-MEM",
      "skill": "MemoryLifecycle",
      "module": "memory-governance",
      "entity": "dashboard",
      "action": "session_close",
      "input_summary": "Automatic lifecycle event",
      "output_summary": "Sessao SES-20260428-0018 encerrada com CHK-MEM-0297",
      "result": "success",
      "files_touched": [
        "docs/control/memory_current_state.json",
        "docs/control/memory_checkpoints.json",
        "docs/control/memory_mutations.json",
        "task.md"
      ],
      "project_id": null
    },
    {
      "id": "RUN-MEM-20260428-0037",
      "timestamp_start": "2026-04-28T13:05:52-03:00",
      "timestamp_end": "2026-04-28T13:05:52-03:00",
      "actor": "system",
      "squad": "SQD-MEM",
      "skill": "MemoryLifecycle",
      "module": "memory-governance",
      "entity": "dashboard",
      "action": "session_start",
      "input_summary": "Automatic lifecycle event",
      "output_summary": "Sessao SES-20260428-0019 iniciada",
      "result": "success",
      "files_touched": [
        "docs/control/memory_current_state.json",
        "docs/control/memory_open_loops.json",
        "docs/control/memory_checkpoints.json",
        "docs/control/memory_decision_log.json",
        "docs/memory/startup_context_latest.md",
        "task.md"
      ],
      "project_id": "sais"
    },
    {
      "id": "RUN-MEM-20260428-0038",
      "timestamp_start": "2026-04-28T13:34:30-03:00",
      "timestamp_end": "2026-04-28T13:34:30-03:00",
      "actor": "system",
      "squad": "SQD-MEM",
      "skill": "MemoryLifecycle",
      "module": "memory-governance",
      "entity": "dashboard",
      "action": "session_close",
      "input_summary": "Automatic lifecycle event",
      "output_summary": "Sessao SES-20260428-0019 encerrada com CHK-MEM-0298",
      "result": "success",
      "files_touched": [
        "docs/control/memory_current_state.json",
        "docs/control/memory_checkpoints.json",
        "docs/control/memory_mutations.json",
        "task.md"
      ],
      "project_id": null
    },
    {
      "id": "RUN-MEM-20260428-0039",
      "timestamp_start": "2026-04-28T13:34:33-03:00",
      "timestamp_end": "2026-04-28T13:34:33-03:00",
      "actor": "system",
      "squad": "SQD-MEM",
      "skill": "MemoryLifecycle",
      "module": "memory-governance",
      "entity": "dashboard",
      "action": "session_start",
      "input_summary": "Automatic lifecycle event",
      "output_summary": "Sessao SES-20260428-0020 iniciada",
      "result": "success",
      "files_touched": [
        "docs/control/memory_current_state.json",
        "docs/control/memory_open_loops.json",
        "docs/control/memory_checkpoints.json",
        "docs/control/memory_decision_log.json",
        "docs/memory/startup_context_latest.md",
        "task.md"
      ],
      "project_id": "sais"
    },
    {
      "id": "RUN-MEM-20260428-0040",
      "timestamp_start": "2026-04-28T13:38:32-03:00",
      "timestamp_end": "2026-04-28T13:38:32-03:00",
      "actor": "system",
      "squad": "SQD-MEM",
      "skill": "MemoryLifecycle",
      "module": "memory-governance",
      "entity": "dashboard",
      "action": "session_close",
      "input_summary": "Automatic lifecycle event",
      "output_summary": "Sessao SES-20260428-0020 encerrada com CHK-MEM-0299",
      "result": "success",
      "files_touched": [
        "docs/control/memory_current_state.json",
        "docs/control/memory_checkpoints.json",
        "docs/control/memory_mutations.json",
        "task.md"
      ],
      "project_id": null
    },
    {
      "id": "RUN-MEM-20260428-0041",
      "timestamp_start": "2026-04-28T13:38:35-03:00",
      "timestamp_end": "2026-04-28T13:38:35-03:00",
      "actor": "system",
      "squad": "SQD-MEM",
      "skill": "MemoryLifecycle",
      "module": "memory-governance",
      "entity": "dashboard",
      "action": "session_start",
      "input_summary": "Automatic lifecycle event",
      "output_summary": "Sessao SES-20260428-0021 iniciada",
      "result": "success",
      "files_touched": [
        "docs/control/memory_current_state.json",
        "docs/control/memory_open_loops.json",
        "docs/control/memory_checkpoints.json",
        "docs/control/memory_decision_log.json",
        "docs/memory/startup_context_latest.md",
        "task.md"
      ],
      "project_id": "sais"
    },
    {
      "id": "RUN-MEM-20260428-0042",
      "timestamp_start": "2026-04-28T14:14:56-03:00",
      "timestamp_end": "2026-04-28T14:14:56-03:00",
      "actor": "system",
      "squad": "SQD-MEM",
      "skill": "MemoryLifecycle",
      "module": "memory-governance",
      "entity": "dashboard",
      "action": "session_close",
      "input_summary": "Automatic lifecycle event",
      "output_summary": "Sessao SES-20260428-0021 encerrada com CHK-MEM-0300",
      "result": "success",
      "files_touched": [
        "docs/control/memory_current_state.json",
        "docs/control/memory_checkpoints.json",
        "docs/control/memory_mutations.json",
        "task.md"
      ],
      "project_id": null
    },
    {
      "id": "RUN-MEM-20260428-0043",
      "timestamp_start": "2026-04-28T14:16:28-03:00",
      "timestamp_end": "2026-04-28T14:16:28-03:00",
      "actor": "system",
      "squad": "SQD-MEM",
      "skill": "MemoryLifecycle",
      "module": "memory-governance",
      "entity": "dashboard",
      "action": "session_start",
      "input_summary": "Automatic lifecycle event",
      "output_summary": "Sessao SES-20260428-0022 iniciada",
      "result": "success",
      "files_touched": [
        "docs/control/memory_current_state.json",
        "docs/control/memory_open_loops.json",
        "docs/control/memory_checkpoints.json",
        "docs/control/memory_decision_log.json",
        "docs/memory/startup_context_latest.md",
        "task.md"
      ],
      "project_id": "sais"
    },
    {
      "id": "RUN-MEM-20260428-0044",
      "timestamp_start": "2026-04-28T14:16:46-03:00",
      "timestamp_end": "2026-04-28T14:16:46-03:00",
      "actor": "system",
      "squad": "SQD-MEM",
      "skill": "MemoryLifecycle",
      "module": "memory-governance",
      "entity": "dashboard",
      "action": "session_close",
      "input_summary": "Automatic lifecycle event",
      "output_summary": "Sessao SES-20260428-0022 encerrada com CHK-MEM-0301",
      "result": "success",
      "files_touched": [
        "docs/control/memory_current_state.json",
        "docs/control/memory_checkpoints.json",
        "docs/control/memory_mutations.json",
        "task.md"
      ],
      "project_id": null
    },
    {
      "id": "RUN-MEM-20260428-0045",
      "timestamp_start": "2026-04-28T14:16:48-03:00",
      "timestamp_end": "2026-04-28T14:16:48-03:00",
      "actor": "system",
      "squad": "SQD-MEM",
      "skill": "MemoryLifecycle",
      "module": "memory-governance",
      "entity": "dashboard",
      "action": "session_start",
      "input_summary": "Automatic lifecycle event",
      "output_summary": "Sessao SES-20260428-0023 iniciada",
      "result": "success",
      "files_touched": [
        "docs/control/memory_current_state.json",
        "docs/control/memory_open_loops.json",
        "docs/control/memory_checkpoints.json",
        "docs/control/memory_decision_log.json",
        "docs/memory/startup_context_latest.md",
        "task.md"
      ],
      "project_id": "sais"
    },
    {
      "id": "RUN-MEM-20260428-0046",
      "timestamp_start": "2026-04-28T15:42:19-03:00",
      "timestamp_end": "2026-04-28T15:42:19-03:00",
      "actor": "system",
      "squad": "SQD-MEM",
      "skill": "MemoryLifecycle",
      "module": "memory-governance",
      "entity": "dashboard",
      "action": "session_close",
      "input_summary": "Automatic lifecycle event",
      "output_summary": "Sessao SES-20260428-0023 encerrada com CHK-MEM-0302",
      "result": "success",
      "files_touched": [
        "docs/control/memory_current_state.json",
        "docs/control/memory_checkpoints.json",
        "docs/control/memory_mutations.json",
        "task.md"
      ],
      "project_id": null
    },
    {
      "id": "RUN-MEM-20260428-0047",
      "timestamp_start": "2026-04-28T15:42:23-03:00",
      "timestamp_end": "2026-04-28T15:42:23-03:00",
      "actor": "system",
      "squad": "SQD-MEM",
      "skill": "MemoryLifecycle",
      "module": "memory-governance",
      "entity": "dashboard",
      "action": "session_start",
      "input_summary": "Automatic lifecycle event",
      "output_summary": "Sessao SES-20260428-0024 iniciada",
      "result": "success",
      "files_touched": [
        "docs/control/memory_current_state.json",
        "docs/control/memory_open_loops.json",
        "docs/control/memory_checkpoints.json",
        "docs/control/memory_decision_log.json",
        "docs/memory/startup_context_latest.md",
        "task.md"
      ],
      "project_id": "sais"
    },
    {
      "id": "RUN-MEM-20260428-0048",
      "timestamp_start": "2026-04-28T15:43:24-03:00",
      "timestamp_end": "2026-04-28T15:43:24-03:00",
      "actor": "system",
      "squad": "SQD-MEM",
      "skill": "MemoryLifecycle",
      "module": "memory-governance",
      "entity": "dashboard",
      "action": "session_close",
      "input_summary": "Automatic lifecycle event",
      "output_summary": "Sessao SES-20260428-0024 encerrada com CHK-MEM-0303",
      "result": "success",
      "files_touched": [
        "docs/control/memory_current_state.json",
        "docs/control/memory_checkpoints.json",
        "docs/control/memory_mutations.json",
        "task.md"
      ],
      "project_id": null
    },
    {
      "id": "RUN-MEM-20260428-0049",
      "timestamp_start": "2026-04-28T20:50:13-03:00",
      "timestamp_end": "2026-04-28T20:50:13-03:00",
      "actor": "system",
      "squad": "SQD-MEM",
      "skill": "MemoryLifecycle",
      "module": "memory-governance",
      "entity": "dashboard",
      "action": "session_start",
      "input_summary": "Automatic lifecycle event",
      "output_summary": "Sessao SES-20260428-0025 iniciada",
      "result": "success",
      "files_touched": [
        "docs/control/memory_current_state.json",
        "docs/control/memory_open_loops.json",
        "docs/control/memory_checkpoints.json",
        "docs/control/memory_decision_log.json",
        "docs/memory/startup_context_latest.md",
        "task.md"
      ],
      "project_id": "sais"
    },
    {
      "id": "RUN-MEM-20260428-0050",
      "timestamp_start": "2026-04-28T21:05:39-03:00",
      "timestamp_end": "2026-04-28T21:05:39-03:00",
      "actor": "system",
      "squad": "SQD-MEM",
      "skill": "MemoryLifecycle",
      "module": "memory-governance",
      "entity": "dashboard",
      "action": "session_close",
      "input_summary": "Automatic lifecycle event",
      "output_summary": "Sessao SES-20260428-0025 encerrada com CHK-MEM-0304",
      "result": "success",
      "files_touched": [
        "docs/control/memory_current_state.json",
        "docs/control/memory_checkpoints.json",
        "docs/control/memory_mutations.json",
        "task.md"
      ],
      "project_id": null
    }
  ],
  "rotated_at": "2026-05-14T23:06:28-03:00"
}
