{
  "source": "https://www.youtube.com/@RimantasPetrauskasEACoder/videos",
  "generated_at": "2026-06-19T11:19:03.534Z",
  "channel_id": "",
  "initial_video_count": 30,
  "total_video_count": 138,
  "continuation_pages_visited": 4,
  "continuation_token_count": 0,
  "videos": [
    {
      "videoId": "FsTw7xKzH8E",
      "title": "New Manual Like Execution Mode in Local Trade Copier for MT4 and MT5",
      "published": "3w ago",
      "duration": "13:20",
      "views": "96",
      "descriptionSnippet": "",
      "url": "https://www.youtube.com/watch?v=FsTw7xKzH8E"
    },
    {
      "videoId": "IMcuK4aCGRY",
      "title": "How to Build & Automate Prop Firm Ready Trading Strategies with FxMagnetic",
      "published": "1y ago",
      "duration": "17:26",
      "views": "508",
      "descriptionSnippet": "",
      "url": "https://www.youtube.com/watch?v=IMcuK4aCGRY"
    },
    {
      "videoId": "7f-I5A9SSoA",
      "title": "This Trade Copier Software Will Save You Thousands—Stop Overpaying for Cloud Copiers!",
      "published": "1y ago",
      "duration": "2:24:21",
      "views": "588",
      "descriptionSnippet": "",
      "url": "https://www.youtube.com/watch?v=7f-I5A9SSoA"
    },
    {
      "videoId": "W1sa2hAg-z0",
      "title": "MACD Settings That Actually Make Money in Forex, Gold, and Nasdaq (Workshop)",
      "published": "1y ago",
      "duration": "1:50:51",
      "views": "2.6K",
      "descriptionSnippet": "",
      "url": "https://www.youtube.com/watch?v=W1sa2hAg-z0"
    },
    {
      "videoId": "_zg5HDjHML4",
      "title": "How to Use MT4 to DxTrade Copier",
      "published": "1y ago",
      "duration": "29:12",
      "views": "1.4K",
      "descriptionSnippet": "",
      "url": "https://www.youtube.com/watch?v=_zg5HDjHML4"
    },
    {
      "videoId": "g6GCO8K7R2k",
      "title": "How To Share Forex Trades With Friends and Family",
      "published": "2y ago",
      "duration": "16:07",
      "views": "1.3K",
      "descriptionSnippet": "",
      "url": "https://www.youtube.com/watch?v=g6GCO8K7R2k"
    },
    {
      "videoId": "TiaPtSBhguQ",
      "title": "Set up MT4 & MT5 Accounts to Copy and Paste Trades From One Forex EA Across Many Metatrader Accounts",
      "published": "2y ago",
      "duration": "15:11",
      "views": "3.9K",
      "descriptionSnippet": "",
      "url": "https://www.youtube.com/watch?v=TiaPtSBhguQ"
    },
    {
      "videoId": "Xgj2mFUI5qE",
      "title": "How To Copy Your Forex and Gold Trades From MT4 to MT5 in One Click",
      "published": "2y ago",
      "duration": "18:39",
      "views": "1.3K",
      "descriptionSnippet": "",
      "url": "https://www.youtube.com/watch?v=Xgj2mFUI5qE"
    },
    {
      "videoId": "0bT7PHaxQbM",
      "title": "How To Easily Copy & Paste Your Forex and Gold Trades From MT5 to MT4 in a Few Simple Steps",
      "published": "2y ago",
      "duration": "20:35",
      "views": "726",
      "descriptionSnippet": "",
      "url": "https://www.youtube.com/watch?v=0bT7PHaxQbM"
    },
    {
      "videoId": "TwthTCQm74A",
      "title": "Easy Way to Copy Trades of Equal Lot Size for All MT4 & MT5 Accounts",
      "published": "2y ago",
      "duration": "7:00",
      "views": "951",
      "descriptionSnippet": "",
      "url": "https://www.youtube.com/watch?v=TwthTCQm74A"
    },
    {
      "videoId": "K6JwObVWivU",
      "title": "How to set different lot sizes for each copier account",
      "published": "2y ago",
      "duration": "7:47",
      "views": "1.9K",
      "descriptionSnippet": "",
      "url": "https://www.youtube.com/watch?v=K6JwObVWivU"
    },
    {
      "videoId": "P9QfYWgbsic",
      "title": "6-Minute Guide to Lightning-Fast Trade Cloning on MT4 & MT5 for Forex, Stocks, Gold, Oil, and More",
      "published": "2y ago",
      "duration": "6:00",
      "views": "5K",
      "descriptionSnippet": "",
      "url": "https://www.youtube.com/watch?v=P9QfYWgbsic"
    },
    {
      "videoId": "LBKToxl__wU",
      "title": "Local Trade Copier Installation on MT4 and MT5 Accounts [2021]",
      "published": "4y ago",
      "duration": "17:39",
      "views": "15K",
      "descriptionSnippet": "",
      "url": "https://www.youtube.com/watch?v=LBKToxl__wU"
    },
    {
      "videoId": "9t3UOJW6l9M",
      "title": "Local Trade Copier DEMO on MT4 and MT5",
      "published": "4y ago",
      "duration": "12:08",
      "views": "7.9K",
      "descriptionSnippet": "",
      "url": "https://www.youtube.com/watch?v=9t3UOJW6l9M"
    },
    {
      "videoId": "FSwUurt79S0",
      "title": "Scalping and Copy Trading on MT4 and MT5 (Best Setup to Avoid Delay and Slippage)",
      "published": "4y ago",
      "duration": "20:20",
      "views": "5K",
      "descriptionSnippet": "",
      "url": "https://www.youtube.com/watch?v=FSwUurt79S0"
    },
    {
      "videoId": "Og2jDZoTLpE",
      "title": "Adding Master Account To Existing MT4 Trade Copier Setup [Checklist included]",
      "published": "4y ago",
      "duration": "20:00",
      "views": "1.6K",
      "descriptionSnippet": "",
      "url": "https://www.youtube.com/watch?v=Og2jDZoTLpE"
    },
    {
      "videoId": "Fu3UA9NLm38",
      "title": "Adding Client Account To Existing MT4 Trade Copier Setup [Checklist included]",
      "published": "4y ago",
      "duration": "14:20",
      "views": "1.1K",
      "descriptionSnippet": "",
      "url": "https://www.youtube.com/watch?v=Fu3UA9NLm38"
    },
    {
      "videoId": "2a9k0B-5daE",
      "title": "Trendline Trader MT4 EA installation on MetaTrader 4",
      "published": "5y ago",
      "duration": "17:30",
      "views": "2.7K",
      "descriptionSnippet": "",
      "url": "https://www.youtube.com/watch?v=2a9k0B-5daE"
    },
    {
      "videoId": "Wb3py0_3KKU",
      "title": "What if MT4 Trade Copier does not always use fixed lot size that I have set?",
      "published": "5y ago",
      "duration": "4:06",
      "views": "546",
      "descriptionSnippet": "",
      "url": "https://www.youtube.com/watch?v=Wb3py0_3KKU"
    },
    {
      "videoId": "Cb_UJ09wVaA",
      "title": "What if I think that the MT4 Trade Copier calculated lot size incorrectly?",
      "published": "5y ago",
      "duration": "3:27",
      "views": "260",
      "descriptionSnippet": "",
      "url": "https://www.youtube.com/watch?v=Cb_UJ09wVaA"
    },
    {
      "videoId": "DawfdhnfJXI",
      "title": "How MT4 Trade Copier automatically adjusts lot sizes between accounts of different currencies",
      "published": "5y ago",
      "duration": "2:34",
      "views": "939",
      "descriptionSnippet": "",
      "url": "https://www.youtube.com/watch?v=DawfdhnfJXI"
    },
    {
      "videoId": "3NEFGOzULu8",
      "title": "How leverage affects the lot size with MT4 Trade Copier",
      "published": "5y ago",
      "duration": "3:33",
      "views": "323",
      "descriptionSnippet": "",
      "url": "https://www.youtube.com/watch?v=3NEFGOzULu8"
    },
    {
      "videoId": "pznLq8C4MTI",
      "title": "MT4 Trade Copier Money Management Mode #8 - LMR Lot Money Ratio",
      "published": "5y ago",
      "duration": "3:01",
      "views": "334",
      "descriptionSnippet": "",
      "url": "https://www.youtube.com/watch?v=pznLq8C4MTI"
    },
    {
      "videoId": "NA19_tYXj0M",
      "title": "MT4 Trade Copier Money Management Mode #7 - Risk Per Trade (Money)",
      "published": "5y ago",
      "duration": "3:30",
      "views": "307",
      "descriptionSnippet": "",
      "url": "https://www.youtube.com/watch?v=NA19_tYXj0M"
    },
    {
      "videoId": "MEW_sOvHCN4",
      "title": "MT4 Trade Copier Money Management Mode #6 - Risk Per Trade in Percentage (%)",
      "published": "5y ago",
      "duration": "4:35",
      "views": "575",
      "descriptionSnippet": "",
      "url": "https://www.youtube.com/watch?v=MEW_sOvHCN4"
    },
    {
      "videoId": "WRtj4BV0nnM",
      "title": "MT4 Trade Copier Money Management Mode #5 - Fixed Lot Size",
      "published": "5y ago",
      "duration": "1:01",
      "views": "469",
      "descriptionSnippet": "",
      "url": "https://www.youtube.com/watch?v=WRtj4BV0nnM"
    },
    {
      "videoId": "kAMfWWocA08",
      "title": "MT4 Trade Copier Money Management Mode #4 - Multiply by X",
      "published": "5y ago",
      "duration": "2:01",
      "views": "302",
      "descriptionSnippet": "",
      "url": "https://www.youtube.com/watch?v=kAMfWWocA08"
    },
    {
      "videoId": "fp9NPG5kERQ",
      "title": "MT4 Trade Copier Money Management Mode #3 - Same lot size as on the master account",
      "published": "5y ago",
      "duration": "1:21",
      "views": "251",
      "descriptionSnippet": "",
      "url": "https://www.youtube.com/watch?v=fp9NPG5kERQ"
    },
    {
      "videoId": "35gu6nbkskA",
      "title": "MT4 Trade Copier Money Management Mode #2 - Auto-Adjust and Multiply by X (AAM)",
      "published": "5y ago",
      "duration": "5:03",
      "views": "367",
      "descriptionSnippet": "",
      "url": "https://www.youtube.com/watch?v=35gu6nbkskA"
    },
    {
      "videoId": "XfmadnluRIc",
      "title": "8 Money Management Modes and 4 Parameters in MT4 Trade Copier",
      "published": "5y ago",
      "duration": "5:22",
      "views": "773",
      "descriptionSnippet": "",
      "url": "https://www.youtube.com/watch?v=XfmadnluRIc"
    },
    {
      "videoId": "sB9Cm3T7ZbM",
      "title": "MT4 Trade Copier Money Management Mode #1 - Auto-Adjust to account size (AA)",
      "published": "5 years ago",
      "duration": "4:47",
      "views": "650 views",
      "descriptionSnippet": "",
      "url": "https://www.youtube.com/watch?v=sB9Cm3T7ZbM"
    },
    {
      "videoId": "CUDNkjQnHBI",
      "title": "Money Management Settings in the MT4 Trade Copier (2020 update)",
      "published": "5 years ago",
      "duration": "46:46",
      "views": "2.6K views",
      "descriptionSnippet": "",
      "url": "https://www.youtube.com/watch?v=CUDNkjQnHBI"
    },
    {
      "videoId": "a_ucSgocJJQ",
      "title": "Trader On Chart demo on MT4 trading platform",
      "published": "5 years ago",
      "duration": "1:00",
      "views": "2.6K views",
      "descriptionSnippet": "",
      "url": "https://www.youtube.com/watch?v=a_ucSgocJJQ"
    },
    {
      "videoId": "IbEaUjrbp1M",
      "title": "How to copy trades from selected MT4 master accounts",
      "published": "5 years ago",
      "duration": "9:24",
      "views": "16K views",
      "descriptionSnippet": "",
      "url": "https://www.youtube.com/watch?v=IbEaUjrbp1M"
    },
    {
      "videoId": "ZPFn9og83Ks",
      "title": "How To Install and Use the Trader On Chart on MT4",
      "published": "6 years ago",
      "duration": "19:32",
      "views": "3.7K views",
      "descriptionSnippet": "",
      "url": "https://www.youtube.com/watch?v=ZPFn9og83Ks"
    },
    {
      "videoId": "F2aKNdAgfSo",
      "title": "The New Signal Magician 1.9.8 With Performance Billing and High Water Mark Functionalities",
      "published": "6 years ago",
      "duration": "1:09:03",
      "views": "1K views",
      "descriptionSnippet": "",
      "url": "https://www.youtube.com/watch?v=F2aKNdAgfSo"
    },
    {
      "videoId": "VzZnzFPBCic",
      "title": "Did you know that it takes several 100 thousand ideas to find good one",
      "published": "6 years ago",
      "duration": "0:41",
      "views": "3.6K views",
      "descriptionSnippet": "",
      "url": "https://www.youtube.com/watch?v=VzZnzFPBCic"
    },
    {
      "videoId": "UCWnn2Ekja4",
      "title": "If You are looking to create - dont skip - having create",
      "published": "6 years ago",
      "duration": "0:41",
      "views": "186 views",
      "descriptionSnippet": "",
      "url": "https://www.youtube.com/watch?v=UCWnn2Ekja4"
    },
    {
      "videoId": "GRkRAkeGd1g",
      "title": "If youre a - dont skip - developed this fx way",
      "published": "6 years ago",
      "duration": "0:42",
      "views": "114 views",
      "descriptionSnippet": "",
      "url": "https://www.youtube.com/watch?v=GRkRAkeGd1g"
    },
    {
      "videoId": "8NBIPjtoYqY",
      "title": "Did you know test 1000's of them at once",
      "published": "6 years ago",
      "duration": "0:41",
      "views": "150 views",
      "descriptionSnippet": "",
      "url": "https://www.youtube.com/watch?v=8NBIPjtoYqY"
    },
    {
      "videoId": "2HD7dB6vG2s",
      "title": "If You use mt4 or 5 - dont skip - having created 100 of thounsands",
      "published": "6 years ago",
      "duration": "0:41",
      "views": "191 views",
      "descriptionSnippet": "",
      "url": "https://www.youtube.com/watch?v=2HD7dB6vG2s"
    },
    {
      "videoId": "nu7sGDN965w",
      "title": "If you use mt4 - So I Created Fx43",
      "published": "6 years ago",
      "duration": "0:41",
      "views": "52K views",
      "descriptionSnippet": "",
      "url": "https://www.youtube.com/watch?v=nu7sGDN965w"
    },
    {
      "videoId": "edSVH838jh8",
      "title": "If you use mt4 or 5 - Dont skip - Developed this Method",
      "published": "6 years ago",
      "duration": "0:42",
      "views": "107K views",
      "descriptionSnippet": "",
      "url": "https://www.youtube.com/watch?v=edSVH838jh8"
    },
    {
      "videoId": "w2T1nZSWFrI",
      "title": "How To Make a Default Template for MT4 Chart",
      "published": "6 years ago",
      "duration": "9:36",
      "views": "8K views",
      "descriptionSnippet": "",
      "url": "https://www.youtube.com/watch?v=w2T1nZSWFrI"
    },
    {
      "videoId": "yt7dymtdacE",
      "title": "How To Download MT4 and Open Forex Demo Account Without a Broker",
      "published": "7 years ago",
      "duration": "35:54",
      "views": "15K views",
      "descriptionSnippet": "",
      "url": "https://www.youtube.com/watch?v=yt7dymtdacE"
    },
    {
      "videoId": "aRqNs8ww0to",
      "title": "How to Create Profitable Trading Strategies Fast (3-Step Process)",
      "published": "7 years ago",
      "duration": "3:47",
      "views": "776 views",
      "descriptionSnippet": "",
      "url": "https://www.youtube.com/watch?v=aRqNs8ww0to"
    },
    {
      "videoId": "DD21mH52oiU",
      "title": "Best and Quickest Way to Install Many MT4 Instances on the Same Computer [or VPS]",
      "published": "7 years ago",
      "duration": "1:07:43",
      "views": "20K views",
      "descriptionSnippet": "",
      "url": "https://www.youtube.com/watch?v=DD21mH52oiU"
    },
    {
      "videoId": "G_vJ1U2I1TI",
      "title": "Why Same MT4 Charts of Different Forex Brokers Showing Different Candles",
      "published": "7 years ago",
      "duration": "18:32",
      "views": "9.3K views",
      "descriptionSnippet": "",
      "url": "https://www.youtube.com/watch?v=G_vJ1U2I1TI"
    },
    {
      "videoId": "bUInnEpb-g8",
      "title": "MT4 Investor Password: Everything you need to know about",
      "published": "8 years ago",
      "duration": "16:30",
      "views": "17K views",
      "descriptionSnippet": "",
      "url": "https://www.youtube.com/watch?v=bUInnEpb-g8"
    },
    {
      "videoId": "yyp9Y8tvUgA",
      "title": "How To Run More Than One Expert Advisor In The Same MT4 On Different Time Frame Of Same Currency",
      "published": "8 years ago",
      "duration": "13:07",
      "views": "20K views",
      "descriptionSnippet": "",
      "url": "https://www.youtube.com/watch?v=yyp9Y8tvUgA"
    },
    {
      "videoId": "ILSSUNdHRKE",
      "title": "Signal Magician - Frequently Asked Questions",
      "published": "9 years ago",
      "duration": "17:28",
      "views": "1.3K views",
      "descriptionSnippet": "",
      "url": "https://www.youtube.com/watch?v=ILSSUNdHRKE"
    },
    {
      "videoId": "xYXouj6CeCk",
      "title": "Hosting MT4 accounts of your customers and settings of Signal Magician",
      "published": "9 years ago",
      "duration": "36:10",
      "views": "1.5K views",
      "descriptionSnippet": "",
      "url": "https://www.youtube.com/watch?v=xYXouj6CeCk"
    },
    {
      "videoId": "qJXA9HXym4M",
      "title": "Copy Unlimited Forex Signal Strategies to Customers via Signal Magician platform",
      "published": "9 years ago",
      "duration": "21:50",
      "views": "2.4K views",
      "descriptionSnippet": "",
      "url": "https://www.youtube.com/watch?v=qJXA9HXym4M"
    },
    {
      "videoId": "UyRWiz_dJ3Q",
      "title": "Demonstration of the Signal Magician control panel and copy trading between MT4",
      "published": "9 years ago",
      "duration": "27:11",
      "views": "4.1K views",
      "descriptionSnippet": "",
      "url": "https://www.youtube.com/watch?v=UyRWiz_dJ3Q"
    },
    {
      "videoId": "T30bCBgjtLU",
      "title": "Why Using Independent Forex Copy Trading Software is Better",
      "published": "9 years ago",
      "duration": "26:52",
      "views": "7.2K views",
      "descriptionSnippet": "",
      "url": "https://www.youtube.com/watch?v=T30bCBgjtLU"
    },
    {
      "videoId": "LPo5unTwIJA",
      "title": "Equity Sentry EA for MT4 - How it works",
      "published": "9 years ago",
      "duration": "1:19:23",
      "views": "12K views",
      "descriptionSnippet": "",
      "url": "https://www.youtube.com/watch?v=LPo5unTwIJA"
    },
    {
      "videoId": "qKSlWePo82A",
      "title": "[Webinar REPLAY] Protect your MT4 funds from a drawdown",
      "published": "9 years ago",
      "duration": "1:00:01",
      "views": "387 views",
      "descriptionSnippet": "",
      "url": "https://www.youtube.com/watch?v=qKSlWePo82A"
    },
    {
      "videoId": "M7mYCORSEys",
      "title": "How to Start Your Own Forex Signal Service - Book",
      "published": "9 years ago",
      "duration": "15:35",
      "views": "7.2K views",
      "descriptionSnippet": "",
      "url": "https://www.youtube.com/watch?v=M7mYCORSEys"
    },
    {
      "videoId": "b-a8nTIFsWQ",
      "title": "Multiple strategy EA names with MyMT4Book on MT4",
      "published": "9 years ago",
      "duration": "6:02",
      "views": "1.4K views",
      "descriptionSnippet": "",
      "url": "https://www.youtube.com/watch?v=b-a8nTIFsWQ"
    },
    {
      "videoId": "noeesazByYI",
      "title": "Analyzing Cairo Forex EA with MyMT4Book on MT4",
      "published": "9 years ago",
      "duration": "16:48",
      "views": "935 views",
      "descriptionSnippet": "",
      "url": "https://www.youtube.com/watch?v=noeesazByYI"
    },
    {
      "videoId": "ViSyaDrcFyU",
      "title": "Repainting MT4 Indicators (5-FX-Scams 2/6)",
      "published": "9 years ago",
      "duration": "23:46",
      "views": "7.5K views",
      "descriptionSnippet": "",
      "url": "https://www.youtube.com/watch?v=ViSyaDrcFyU"
    },
    {
      "videoId": "NGE59j9A6dM",
      "title": "Forex signal scams (5-FX-Scams 3/6)",
      "published": "9 years ago",
      "duration": "20:30",
      "views": "2.1K views",
      "descriptionSnippet": "",
      "url": "https://www.youtube.com/watch?v=NGE59j9A6dM"
    },
    {
      "videoId": "0cwNbFTIOv4",
      "title": "How to identify Forex scams in 5 steps (5-FX-Scams 1/6)",
      "published": "9 years ago",
      "duration": "12:29",
      "views": "5.3K views",
      "descriptionSnippet": "",
      "url": "https://www.youtube.com/watch?v=0cwNbFTIOv4"
    },
    {
      "videoId": "EdS9OpLBpOI",
      "title": "Scams are everywhere, not just in Forex (5-FX-Scams Intro)",
      "published": "9 years ago",
      "duration": "20:51",
      "views": "2.8K views",
      "descriptionSnippet": "",
      "url": "https://www.youtube.com/watch?v=EdS9OpLBpOI"
    },
    {
      "videoId": "5pRJ5g9UNGo",
      "title": "Copy Forex Trades with Different Risk Parameters for Each Pair",
      "published": "9 years ago",
      "duration": "11:41",
      "views": "1.6K views",
      "descriptionSnippet": "",
      "url": "https://www.youtube.com/watch?v=5pRJ5g9UNGo"
    },
    {
      "videoId": "xKdO40_YSU8",
      "title": "Fast Forex Trade Copier (10 orders copied in under 1 second)",
      "published": "9 years ago",
      "duration": "15:36",
      "views": "18K views",
      "descriptionSnippet": "",
      "url": "https://www.youtube.com/watch?v=xKdO40_YSU8"
    },
    {
      "videoId": "9nlZZ2zKa_M",
      "title": "Creating Multi-Currency Algotrading Forex Strategy on 9 Instruments",
      "published": "9 years ago",
      "duration": "20:05",
      "views": "17K views",
      "descriptionSnippet": "",
      "url": "https://www.youtube.com/watch?v=9nlZZ2zKa_M"
    },
    {
      "videoId": "-Pm4e5RFHIM",
      "title": "Portfoliolizer: Multi-Market Trading Strategy Scanner",
      "published": "9 years ago",
      "duration": "13:51",
      "views": "2.1K views",
      "descriptionSnippet": "",
      "url": "https://www.youtube.com/watch?v=-Pm4e5RFHIM"
    },
    {
      "videoId": "qcd_VBaR1P0",
      "title": "99% Backtesting on MT4 with the new Tick Data Suite v2",
      "published": "9 years ago",
      "duration": "23:44",
      "views": "38K views",
      "descriptionSnippet": "",
      "url": "https://www.youtube.com/watch?v=qcd_VBaR1P0"
    },
    {
      "videoId": "cVJuF6azCeo",
      "title": "Trendline Trader EA explanation on MT4",
      "published": "9 years ago",
      "duration": "14:40",
      "views": "15K views",
      "descriptionSnippet": "",
      "url": "https://www.youtube.com/watch?v=cVJuF6azCeo"
    },
    {
      "videoId": "0OUZkUSPNDY",
      "title": "CloseBy transactions copied to MT4 client account",
      "published": "9 years ago",
      "duration": "6:10",
      "views": "674 views",
      "descriptionSnippet": "",
      "url": "https://www.youtube.com/watch?v=0OUZkUSPNDY"
    },
    {
      "videoId": "Lbsr8HSGPxU",
      "title": "Partial close transactions copied to MT4 client account",
      "published": "9 years ago",
      "duration": "5:20",
      "views": "892 views",
      "descriptionSnippet": "",
      "url": "https://www.youtube.com/watch?v=Lbsr8HSGPxU"
    },
    {
      "videoId": "e3a8Evwcs70",
      "title": "Copying only certain types of trades on MT4",
      "published": "9 years ago",
      "duration": "3:42",
      "views": "713 views",
      "descriptionSnippet": "",
      "url": "https://www.youtube.com/watch?v=e3a8Evwcs70"
    },
    {
      "videoId": "Ci3I9IjpHfU",
      "title": "SplitLots function explained for MT4 trade copier app",
      "published": "9 years ago",
      "duration": "8:36",
      "views": "11K views",
      "descriptionSnippet": "",
      "url": "https://www.youtube.com/watch?v=Ci3I9IjpHfU"
    },
    {
      "videoId": "1C5X2_ncsFs",
      "title": "Ghost trades in copy trading and how to remove them",
      "published": "9 years ago",
      "duration": "8:41",
      "views": "2.2K views",
      "descriptionSnippet": "",
      "url": "https://www.youtube.com/watch?v=1C5X2_ncsFs"
    },
    {
      "videoId": "l5uVT7zK3Y8",
      "title": "Copy trades from MT4 read only investor password access",
      "published": "9 years ago",
      "duration": "7:54",
      "views": "50K views",
      "descriptionSnippet": "",
      "url": "https://www.youtube.com/watch?v=l5uVT7zK3Y8"
    },
    {
      "videoId": "7h4BUX1lZok",
      "title": "MT4 Trade Copier doesn't conflict with other Expert Advisors",
      "published": "9 years ago",
      "duration": "7:14",
      "views": "1.7K views",
      "descriptionSnippet": "",
      "url": "https://www.youtube.com/watch?v=7h4BUX1lZok"
    },
    {
      "videoId": "-Osdr6wrfa4",
      "title": "Set trade copier to accept or ignore open/modify/close commands",
      "published": "10 years ago",
      "duration": "9:22",
      "views": "3.9K views",
      "descriptionSnippet": "",
      "url": "https://www.youtube.com/watch?v=-Osdr6wrfa4"
    },
    {
      "videoId": "5r5-D6o1ma4",
      "title": "Trade Copier waiting for stop loss or take profit to be hit",
      "published": "10 years ago",
      "duration": "4:16",
      "views": "1.1K views",
      "descriptionSnippet": "",
      "url": "https://www.youtube.com/watch?v=5r5-D6o1ma4"
    },
    {
      "videoId": "BaaJYZPaXgs",
      "title": "How to change trade instrument on MT4 during copy trading (EURUSD to USDCHF)",
      "published": "10 years ago",
      "duration": "7:25",
      "views": "1.3K views",
      "descriptionSnippet": "",
      "url": "https://www.youtube.com/watch?v=BaaJYZPaXgs"
    },
    {
      "videoId": "Vmeg6XM1sQg",
      "title": "Stop & Close at certain level of closed + open positions",
      "published": "10 years ago",
      "duration": "9:16",
      "views": "914 views",
      "descriptionSnippet": "",
      "url": "https://www.youtube.com/watch?v=Vmeg6XM1sQg"
    },
    {
      "videoId": "FMB_uThB4QM",
      "title": "Stop & Close at certain open profit with MT4 Local Trade Copier",
      "published": "10 years ago",
      "duration": "2:13",
      "views": "2.1K views",
      "descriptionSnippet": "",
      "url": "https://www.youtube.com/watch?v=FMB_uThB4QM"
    },
    {
      "videoId": "JHiw4l6WUA0",
      "title": "Allocating account size for copy trading position sizing",
      "published": "10 years ago",
      "duration": "4:37",
      "views": "2.3K views",
      "descriptionSnippet": "",
      "url": "https://www.youtube.com/watch?v=JHiw4l6WUA0"
    },
    {
      "videoId": "TK-B13XZ-60",
      "title": "Signal Magician 1.9.6 changes and new features",
      "published": "10 years ago",
      "duration": "30:36",
      "views": "701 views",
      "descriptionSnippet": "",
      "url": "https://www.youtube.com/watch?v=TK-B13XZ-60"
    },
    {
      "videoId": "PI63yL5xTik",
      "title": "How to update Signal Magician to version 1.9.6",
      "published": "10 years ago",
      "duration": "19:53",
      "views": "378 views",
      "descriptionSnippet": "",
      "url": "https://www.youtube.com/watch?v=PI63yL5xTik"
    },
    {
      "videoId": "EfMCmltuImg",
      "title": "Copying trades with LTC when symbol names are different between MT4 accounts",
      "published": "10 years ago",
      "duration": "7:13",
      "views": "4.2K views",
      "descriptionSnippet": "",
      "url": "https://www.youtube.com/watch?v=EfMCmltuImg"
    },
    {
      "videoId": "-zY7VsHJs3w",
      "title": "Stop & close at certain equity level with Local Trade Copier on MT4",
      "published": "10 years ago",
      "duration": "5:47",
      "views": "1.3K views",
      "descriptionSnippet": "",
      "url": "https://www.youtube.com/watch?v=-zY7VsHJs3w"
    },
    {
      "videoId": "qwDDiTBKg-o",
      "title": "Local Trade Copier Has Many Risk Parameters in Client EA",
      "published": "10 years ago",
      "duration": "18:45",
      "views": "5.8K views",
      "descriptionSnippet": "",
      "url": "https://www.youtube.com/watch?v=qwDDiTBKg-o"
    },
    {
      "videoId": "UAzZ0N6ga9s",
      "title": "Copying Forex trades from one MT4 master into three MT4 client accounts",
      "published": "10 years ago",
      "duration": "11:43",
      "views": "28K views",
      "descriptionSnippet": "",
      "url": "https://www.youtube.com/watch?v=UAzZ0N6ga9s"
    },
    {
      "videoId": "wFuKdjBLA9s",
      "title": "Local Trade Copier installation on MT4 trading platform",
      "published": "10 years ago",
      "duration": "10:35",
      "views": "15K views",
      "descriptionSnippet": "",
      "url": "https://www.youtube.com/watch?v=wFuKdjBLA9s"
    },
    {
      "videoId": "vlBolfRerz4",
      "title": "Local Trade Copier for MT4 explained to Forex traders",
      "published": "10 years ago",
      "duration": "13:24",
      "views": "29K views",
      "descriptionSnippet": "",
      "url": "https://www.youtube.com/watch?v=vlBolfRerz4"
    },
    {
      "videoId": "cCf7P2_BTEI",
      "title": "MyMT4Book indicator for instant MT4 analysis",
      "published": "10 years ago",
      "duration": "16:46",
      "views": "10K views",
      "descriptionSnippet": "",
      "url": "https://www.youtube.com/watch?v=cCf7P2_BTEI"
    },
    {
      "videoId": "t-wPANBE9QQ",
      "title": "Trader On Chart v1.7 presentation - MT4 App for Forex Trading",
      "published": "10 years ago",
      "duration": "23:49",
      "views": "21K views",
      "descriptionSnippet": "",
      "url": "https://www.youtube.com/watch?v=t-wPANBE9QQ"
    },
    {
      "videoId": "wiXker-Zjhs",
      "title": "Forex Local Trade Copier v2.6 released for MT4 client terminal",
      "published": "11 years ago",
      "duration": "4:38",
      "views": "1.1K views",
      "descriptionSnippet": "",
      "url": "https://www.youtube.com/watch?v=wiXker-Zjhs"
    },
    {
      "videoId": "pEgq_qccVdM",
      "title": "The use of Magic Numbers with the Local Trade Copier on MT4 platform",
      "published": "11 years ago",
      "duration": "2:20",
      "views": "1.3K views",
      "descriptionSnippet": "",
      "url": "https://www.youtube.com/watch?v=pEgq_qccVdM"
    },
    {
      "videoId": "BaU6zWcSo5Y",
      "title": "Remote Trade Copier update instructions",
      "published": "11 years ago",
      "duration": "16:45",
      "views": "1.6K views",
      "descriptionSnippet": "",
      "url": "https://www.youtube.com/watch?v=BaU6zWcSo5Y"
    },
    {
      "videoId": "Nvz76TgvnIs",
      "title": "MT4 Trade Copier v2.5 released for MT4 platform",
      "published": "11 years ago",
      "duration": "3:50",
      "views": "557 views",
      "descriptionSnippet": "",
      "url": "https://www.youtube.com/watch?v=Nvz76TgvnIs"
    },
    {
      "videoId": "E2nyPx3_s5g",
      "title": "The new Local Trade Copier v2.4 for MT4 platform",
      "published": "11 years ago",
      "duration": "8:58",
      "views": "892 views",
      "descriptionSnippet": "",
      "url": "https://www.youtube.com/watch?v=E2nyPx3_s5g"
    },
    {
      "videoId": "zBemxjfxbXc",
      "title": "Local Trade Copier and error 133 on the MT4 Client Account",
      "published": "11 years ago",
      "duration": "1:49",
      "views": "2.9K views",
      "descriptionSnippet": "",
      "url": "https://www.youtube.com/watch?v=zBemxjfxbXc"
    },
    {
      "videoId": "jvXpfo8r9uM",
      "title": "Programming MT4 to Re-Enter the Forex Market After Pullback",
      "published": "11 years ago",
      "duration": "13:11",
      "views": "12K views",
      "descriptionSnippet": "",
      "url": "https://www.youtube.com/watch?v=jvXpfo8r9uM"
    },
    {
      "videoId": "cK5YZmocAzw",
      "title": "How to Replicate Forex Trades from MT4 Mobile",
      "published": "11 years ago",
      "duration": "19:51",
      "views": "15K views",
      "descriptionSnippet": "",
      "url": "https://www.youtube.com/watch?v=cK5YZmocAzw"
    },
    {
      "videoId": "Uk8n7c3zbOM",
      "title": "Few bug fixes and new features for LTC v2.3",
      "published": "11 years ago",
      "duration": "7:25",
      "views": "120 views",
      "descriptionSnippet": "",
      "url": "https://www.youtube.com/watch?v=Uk8n7c3zbOM"
    },
    {
      "videoId": "331D5DXaSGQ",
      "title": "Local Trade Copier v2.3 for MT4 released",
      "published": "11 years ago",
      "duration": "16:47",
      "views": "489 views",
      "descriptionSnippet": "",
      "url": "https://www.youtube.com/watch?v=331D5DXaSGQ"
    },
    {
      "videoId": "sf5-_y-kc6w",
      "title": "Auto calculate FOREX risk entry stop settings with just 1 click",
      "published": "11 years ago",
      "duration": "3:39",
      "views": "16K views",
      "descriptionSnippet": "",
      "url": "https://www.youtube.com/watch?v=sf5-_y-kc6w"
    },
    {
      "videoId": "MK8sqYHZU64",
      "title": "Split master MT4 trades into multiple positions on the client account to avoid 50 lot size limit",
      "published": "12 years ago",
      "duration": "1:19",
      "views": "2K views",
      "descriptionSnippet": "",
      "url": "https://www.youtube.com/watch?v=MK8sqYHZU64"
    },
    {
      "videoId": "p_hqlAXN8ts",
      "title": "What to do when Local Trade Copier does not copy trades",
      "published": "12 years ago",
      "duration": "5:15",
      "views": "1.3K views",
      "descriptionSnippet": "",
      "url": "https://www.youtube.com/watch?v=p_hqlAXN8ts"
    },
    {
      "videoId": "54sJC5TenV8",
      "title": "Copying reversed Forex trades on MT4 account to itself",
      "published": "12 years ago",
      "duration": "1:46",
      "views": "1.9K views",
      "descriptionSnippet": "",
      "url": "https://www.youtube.com/watch?v=54sJC5TenV8"
    },
    {
      "videoId": "CGgsGw68m5E",
      "title": "Red question mark icon in the Local Trade Copier dashboard",
      "published": "12 years ago",
      "duration": "1:50",
      "views": "304 views",
      "descriptionSnippet": "",
      "url": "https://www.youtube.com/watch?v=CGgsGw68m5E"
    },
    {
      "videoId": "nO5UVkMQdjo",
      "title": "The difference between Signal_Provider_ID and the FilterMasterAccounts",
      "published": "12 years ago",
      "duration": "2:24",
      "views": "737 views",
      "descriptionSnippet": "",
      "url": "https://www.youtube.com/watch?v=nO5UVkMQdjo"
    },
    {
      "videoId": "t2o2_ElSY-Y",
      "title": "Can LTC Server EA set the stop loss and take profit on my trades?",
      "published": "12 years ago",
      "duration": "2:12",
      "views": "346 views",
      "descriptionSnippet": "",
      "url": "https://www.youtube.com/watch?v=t2o2_ElSY-Y"
    },
    {
      "videoId": "kqtyPrDqQ2c",
      "title": "Rebooting Local Trade Copier client and server with open positions",
      "published": "12 years ago",
      "duration": "2:04",
      "views": "300 views",
      "descriptionSnippet": "",
      "url": "https://www.youtube.com/watch?v=kqtyPrDqQ2c"
    },
    {
      "videoId": "Ipoxl9PMEYc",
      "title": "Copy forex trades from two MT4 masters into a single slave account using LTC",
      "published": "12 years ago",
      "duration": "2:52",
      "views": "2.3K views",
      "descriptionSnippet": "",
      "url": "https://www.youtube.com/watch?v=Ipoxl9PMEYc"
    },
    {
      "videoId": "9WBHIDwqeY8",
      "title": "Sending trades to an unlimited receivers over the internet using Local Trade Copier",
      "published": "12 years ago",
      "duration": "1:21",
      "views": "484 views",
      "descriptionSnippet": "",
      "url": "https://www.youtube.com/watch?v=9WBHIDwqeY8"
    },
    {
      "videoId": "K3R487aMMWc",
      "title": "How can I make the Local Trade Copier copy trades with the exact same lot size, no matter what?",
      "published": "12 years ago",
      "duration": "0:38",
      "views": "848 views",
      "descriptionSnippet": "",
      "url": "https://www.youtube.com/watch?v=K3R487aMMWc"
    },
    {
      "videoId": "fkWGczXcOsE",
      "title": "Can I copy reverse trades with LTC from a demo to a real money MT4 account?",
      "published": "12 years ago",
      "duration": "0:46",
      "views": "1.1K views",
      "descriptionSnippet": "",
      "url": "https://www.youtube.com/watch?v=fkWGczXcOsE"
    },
    {
      "videoId": "LpI-rCmIQCk",
      "title": "Local Trade Copier v2 2 update released for MT4 Build 600",
      "published": "12 years ago",
      "duration": "1:56",
      "views": "1.3K views",
      "descriptionSnippet": "",
      "url": "https://www.youtube.com/watch?v=LpI-rCmIQCk"
    },
    {
      "videoId": "9Nfxoy2R1YM",
      "title": "Local Trade Copier speed of execution demonstration on MT4",
      "published": "12 years ago",
      "duration": "3:34",
      "views": "6.5K views",
      "descriptionSnippet": "",
      "url": "https://www.youtube.com/watch?v=9Nfxoy2R1YM"
    },
    {
      "videoId": "Vpltlx5WO1U",
      "title": "Trader on Chart - The 1-Click Forex Trading EA for Metatrader 4",
      "published": "13 years ago",
      "duration": "5:27",
      "views": "15K views",
      "descriptionSnippet": "",
      "url": "https://www.youtube.com/watch?v=Vpltlx5WO1U"
    },
    {
      "videoId": "bCanuewC1Bs",
      "title": "Partial Close (Scale out) option in MT4 Expert Advisor",
      "published": "13 years ago",
      "duration": "1:55",
      "views": "6.1K views",
      "descriptionSnippet": "",
      "url": "https://www.youtube.com/watch?v=bCanuewC1Bs"
    },
    {
      "videoId": "G9Bdcls9p2I",
      "title": "Trader on Chart v1.5 - One Click Trading for any MT4 client terminal",
      "published": "13 years ago",
      "duration": "7:02",
      "views": "21K views",
      "descriptionSnippet": "",
      "url": "https://www.youtube.com/watch?v=G9Bdcls9p2I"
    },
    {
      "videoId": "70IDbp_lqOM",
      "title": "Stealth EA - Dashboard",
      "published": "13 years ago",
      "duration": "3:00",
      "views": "969 views",
      "descriptionSnippet": "",
      "url": "https://www.youtube.com/watch?v=70IDbp_lqOM"
    },
    {
      "videoId": "qb2vNuJ3aVk",
      "title": "Stealth EA - Stop and Reverse Trading",
      "published": "13 years ago",
      "duration": "1:12",
      "views": "2.7K views",
      "descriptionSnippet": "",
      "url": "https://www.youtube.com/watch?v=qb2vNuJ3aVk"
    },
    {
      "videoId": "ZXN2bF-9-7g",
      "title": "Stealth EA - Close Trade By Ticket Number Using \"Close Lines\"",
      "published": "13 years ago",
      "duration": "1:46",
      "views": "500 views",
      "descriptionSnippet": "",
      "url": "https://www.youtube.com/watch?v=ZXN2bF-9-7g"
    },
    {
      "videoId": "71RtFcLqK1I",
      "title": "Stealth EA - Low Take Profit and Stop Loss levels of 1 pip",
      "published": "13 years ago",
      "duration": "0:51",
      "views": "2.6K views",
      "descriptionSnippet": "",
      "url": "https://www.youtube.com/watch?v=71RtFcLqK1I"
    },
    {
      "videoId": "WenwXe407u0",
      "title": "Stealth EA - 1-Click-Trading for Fast Trade Open",
      "published": "13 years ago",
      "duration": "0:44",
      "views": "698 views",
      "descriptionSnippet": "",
      "url": "https://www.youtube.com/watch?v=WenwXe407u0"
    },
    {
      "videoId": "FW_NhAX3SJE",
      "title": "Stealth EA - One Cancels Other (OCO)",
      "published": "13 years ago",
      "duration": "0:42",
      "views": "1.1K views",
      "descriptionSnippet": "",
      "url": "https://www.youtube.com/watch?v=FW_NhAX3SJE"
    },
    {
      "videoId": "CskRzx3rAbA",
      "title": "Stealth EA - Hidden Pending Orders with Expiration and OCO",
      "published": "13 years ago",
      "duration": "3:47",
      "views": "4.9K views",
      "descriptionSnippet": "",
      "url": "https://www.youtube.com/watch?v=CskRzx3rAbA"
    },
    {
      "videoId": "WYQOKl9Doag",
      "title": "Stealth EA - Hidden Pending Orders",
      "published": "13 years ago",
      "duration": "2:42",
      "views": "1.7K views",
      "descriptionSnippet": "",
      "url": "https://www.youtube.com/watch?v=WYQOKl9Doag"
    },
    {
      "videoId": "iHxklIzS6E4",
      "title": "Stealth EA - Fake, Real Stop Loss & Take Profit",
      "published": "13 years ago",
      "duration": "0:48",
      "views": "1.2K views",
      "descriptionSnippet": "",
      "url": "https://www.youtube.com/watch?v=iHxklIzS6E4"
    },
    {
      "videoId": "hMK2-ms-PKA",
      "title": "Stealth EA - Moving Stop Loss & Take Profit with your mouse",
      "published": "13 years ago",
      "duration": "0:42",
      "views": "2.7K views",
      "descriptionSnippet": "",
      "url": "https://www.youtube.com/watch?v=hMK2-ms-PKA"
    },
    {
      "videoId": "suPTigb_Bkc",
      "title": "Stealth EA - Hidden Stop Loss & Take Profit",
      "published": "13 years ago",
      "duration": "1:05",
      "views": "3.5K views",
      "descriptionSnippet": "",
      "url": "https://www.youtube.com/watch?v=suPTigb_Bkc"
    },
    {
      "videoId": "7zCzY3d5h4s",
      "title": "Stealth EA - How can you close the trades at the designated time",
      "published": "13 years ago",
      "duration": "3:52",
      "views": "470 views",
      "descriptionSnippet": "",
      "url": "https://www.youtube.com/watch?v=7zCzY3d5h4s"
    },
    {
      "videoId": "rjjDg4jB9t0",
      "title": "Stealth EA - How can you adjust hidden stop loss and take profit values with your mouse easily",
      "published": "13 years ago",
      "duration": "6:25",
      "views": "2.9K views",
      "descriptionSnippet": "",
      "url": "https://www.youtube.com/watch?v=rjjDg4jB9t0"
    },
    {
      "videoId": "Rqmgh4NO6BU",
      "title": "Stealth EA - Feature-rich and User-friendly Trade Manager for MT4",
      "published": "13 years ago",
      "duration": "8:59",
      "views": "7K views",
      "descriptionSnippet": "",
      "url": "https://www.youtube.com/watch?v=Rqmgh4NO6BU"
    },
    {
      "videoId": "p2iTGW3CD0M",
      "title": "Stealth EA for MT4 to Hide Forex Stop Loss and Take Profit",
      "published": "13 years ago",
      "duration": "1:15",
      "views": "9.5K views",
      "descriptionSnippet": "",
      "url": "https://www.youtube.com/watch?v=p2iTGW3CD0M"
    },
    {
      "videoId": "3ymj6y9kUMw",
      "title": "Copy & Reverse Forex Trades between MT4 accounts with the Local Trade Copier by EA Coder",
      "published": "13 years ago",
      "duration": "4:07",
      "views": "11K views",
      "descriptionSnippet": "",
      "url": "https://www.youtube.com/watch?v=3ymj6y9kUMw"
    },
    {
      "videoId": "ZmTvr8WT0p0",
      "title": "Multiple trades are being copied using Local Trade Copier for Metatrader 4 by EA Coder",
      "published": "14 years ago",
      "duration": "2:29",
      "views": "5.1K views",
      "descriptionSnippet": "",
      "url": "https://www.youtube.com/watch?v=ZmTvr8WT0p0"
    },
    {
      "videoId": "MiGBFoJ2bcU",
      "title": "Copy trades between two MT4 account using Local Trade Copier by EA Coder",
      "published": "14 years ago",
      "duration": "2:56",
      "views": "36K views",
      "descriptionSnippet": "",
      "url": "https://www.youtube.com/watch?v=MiGBFoJ2bcU"
    }
  ],
  "continuation_tokens_remaining": []
}